{
  "servers": [
    {
      "name": "val1",
      "serverIP": "109.105.61.119",
      "QueryPort": "27070",
      "GamePort": "7070"
    },
    {
      "name": "cen1",
      "serverIP": "109.105.61.119",
      "QueryPort": "27020",
      "GamePort": "7020"
    },
    {
      "name": "gen1",
      "serverIP": "109.105.61.119",
      "QueryPort": "27080",
      "GamePort": "7080"
    },
    {
      "name": "abe1",
      "serverIP": "109.105.61.119",
      "QueryPort": "27010",
      "GamePort": "7010"
    },
    {
      "name": "ext1",
      "serverIP": "109.105.61.119",
      "QueryPort": "27030",
      "GamePort": "7030"
    },
    {
      "name": "rag1",
      "serverIP": "109.105.61.119",
      "QueryPort": "27050",
      "GamePort": "7050"
    },
    {
      "name": "isl1",
      "serverIP": "109.105.61.119",
      "QueryPort": "27040",
      "GamePort": "7040"
    }
  ]
}